poi/__init__.py
poi/book.py
poi/nodes.py
poi/py.typed
poi/sheet.py
poi/utils.py
poi/visitors/__init__.py
poi/visitors/printer.py
poi/visitors/writer.py
poi/writer.py
poi-1.2.6.dist-info/WHEEL
poi-1.2.6.dist-info/METADATA
poi-1.2.6.dist-info/RECORD
