Metadata-Version: 2.4
Name: poi
Version: 1.2.6
Summary: Write Excel XLSX declaratively.
Keywords: xlsx,xlswriter,excel,declarative
Author: Ryan Wang
Author-email: Ryan Wang < hwwangwang@gmail.com>
License-Expression: MIT
Classifier: Topic :: Software Development :: Libraries
Classifier: Topic :: Software Development :: Libraries :: Python Modules
Classifier: Programming Language :: Python :: 3.9
Classifier: Programming Language :: Python :: 3.10
Classifier: Programming Language :: Python :: 3.11
Classifier: Programming Language :: Python :: 3.12
Requires-Dist: xlsxwriter>=3.2.5
Requires-Python: >=3.9
